ApacheDoc/README.md
ApacheDoc/__init__.py
ApacheDoc/__main__.py
ApacheDoc/file.epub
ApacheDoc/index.html
ApacheDoc/css/__init__.py
ApacheDoc/css/annotations.css
ApacheDoc/css/main.css
ApacheDoc/css/normalize.css
ApacheDoc/css/popup.css
ApacheDoc/font/__init__.py
ApacheDoc/font/fontello.eot
ApacheDoc/font/fontello.svg
ApacheDoc/font/fontello.ttf
ApacheDoc/font/fontello.woff
ApacheDoc/img/__init__.py
ApacheDoc/img/annotator-glyph-sprite.png
ApacheDoc/img/annotator-icon-sprite.png
ApacheDoc/img/apple-touch-icon.png
ApacheDoc/img/cancelfullscreen.png
ApacheDoc/img/close.png
ApacheDoc/img/fullscreen.png
ApacheDoc/img/loader.gif
ApacheDoc/img/menu-icon.png
ApacheDoc/img/save.png
ApacheDoc/img/saved.png
ApacheDoc/img/settings-s.png
ApacheDoc/img/settings.png
ApacheDoc/img/star.png
ApacheDoc/js/__init__.py
ApacheDoc/js/epub.js
ApacheDoc/js/epub.min.js
ApacheDoc/js/epub.min.map
ApacheDoc/js/hooks.min.js
ApacheDoc/js/hooks.min.map
ApacheDoc/js/reader.js
ApacheDoc/js/reader.js.map
ApacheDoc/js/reader.min.js
ApacheDoc/js/reader.min.map
ApacheDoc/js/hooks/__init__.py
ApacheDoc/js/hooks/extensions/__init__.py
ApacheDoc/js/hooks/extensions/highlight.js
ApacheDoc/js/libs/__init__.py
ApacheDoc/js/libs/jquery.min.js
ApacheDoc/js/libs/localforage.min.js
ApacheDoc/js/libs/screenfull.js
ApacheDoc/js/libs/screenfull.min.js
ApacheDoc/js/libs/zip.min.js
ApacheDoc/js/plugins/__init__.py
ApacheDoc/js/plugins/hypothesis.js
ApacheDoc/js/plugins/search.js
apache_doc-2024.2.29.0.dist-info/METADATA
apache_doc-2024.2.29.0.dist-info/WHEEL
apache_doc-2024.2.29.0.dist-info/entry_points.txt
apache_doc-2024.2.29.0.dist-info/top_level.txt
apache_doc-2024.2.29.0.dist-info/RECORD
